{
  "18894808": [
    "menu.jpg"
  ],
  "18535169": [
    "featured.jpg",
    "menu3.jpg",
    "menu2.jpg",
    "menu1.jpg"
  ],
  "18556255": [
    "menu.jpg"
  ],
  "16613837": [
    "featured.jpg"
  ],
  "17744589": [
    "featured.jpg"
  ],
  "18793809": [
    "featured.jpg"
  ],
  "17841648": [
    "featured.jpg",
    "menu2.jpg",
    "menu1.jpg"
  ],
  "18690158": [
    "menu3.jpg",
    "menu2.jpg",
    "menu1.jpg",
    "menu5.jpg",
    "menu4.jpg",
    "menu6.jpg"
  ],
  "16611534": [
    "featured.jpg"
  ],
  "18524079": [
    "featured.jpg",
    "menu3.jpg",
    "menu2.jpg",
    "menu1.jpg",
    "menu5.jpg",
    "menu4.jpg"
  ],
  "16603466": [
    "featured.jpg"
  ],
  "18386126": [
    "featured.jpg"
  ],
  "16601593": [
    "featured.jpg",
    "menu.jpg"
  ],
  "18553113": [
    "featured.jpg",
    "menu.jpg"
  ],
  "18962836": [
    "featured.jpg"
  ],
  "16581844": [
    "featured.jpg",
    "menu2.jpg",
    "menu1.jpg"
  ],
  "18878420": [
    "featured.jpg",
    "menu.jpg"
  ],
  "16566675": [
    "featured.jpg",
    "menu.jpg"
  ],
  "19166157": [
    "menu.jpg"
  ],
  "16601931": [
    "featured.jpg"
  ],
  "18401470": [
    "featured.jpg",
    "menu3.jpg",
    "menu2.jpg",
    "menu1.jpg",
    "menu4.jpg"
  ],
  "16588992": [
    "featured.jpg"
  ],
  "17841649": [
    "featured.jpg"
  ],
  "18709860": [
    "featured.jpg",
    "menu.jpg"
  ],
  "18759946": [
    "featured.jpg",
    "menu2.jpg",
    "menu1.jpg"
  ],
  "18676447": [
    "featured.jpg",
    "menu3.jpg",
    "menu2.jpg",
    "menu1.jpg",
    "menu4.jpg"
  ],
  "17841682": [
    "menu.jpg"
  ],
  "16582035": [
    "featured.jpg",
    "menu.jpg"
  ],
  "16580550": [
    "featured.jpg"
  ],
  "15547233": [
    "featured.jpg",
    "menu2.jpg",
    "menu1.jpg"
  ],
  "17744544": [
    "featured.jpg"
  ],
  "16605558": [
    "featured.jpg"
  ],
  "18361516": [
    "featured.jpg",
    "menu3.jpg",
    "menu2.jpg",
    "menu1.jpg"
  ],
  "16601796": [
    "featured.jpg",
    "menu.jpg"
  ],
  "17744984": [
    "menu.jpg"
  ],
  "18508870": [
    "featured.jpg"
  ],
  "18529109": [
    "featured.jpg",
    "menu.jpg"
  ],
  "18445592": [
    "featured.jpg",
    "menu2.jpg",
    "menu1.jpg"
  ],
  "16594338": [
    "featured.jpg",
    "menu.jpg"
  ],
  "16600738": [
    "featured.jpg",
    "menu.jpg"
  ],
  "18300657": [
    "featured.jpg",
    "menu.jpg"
  ],
  "18898723": [
    "featured.jpg",
    "menu.jpg"
  ],
  "17989236": [
    "featured.jpg",
    "menu.jpg"
  ],
  "18793786": [
    "menu.jpg"
  ],
  "18623567": [
    "featured.jpg"
  ],
  "16601046": [
    "featured.jpg"
  ],
  "18664092": [
    "menu3.jpg",
    "menu2.jpg",
    "menu1.jpg"
  ],
  "18806311": [
    "featured.jpg",
    "menu2.jpg",
    "menu1.jpg"
  ],
  "18285760": [
    "featured.jpg",
    "menu.jpg"
  ],
  "17892198": [
    "featured.jpg"
  ],
  "18445610": [
    "featured.jpg",
    "menu2.jpg",
    "menu1.jpg"
  ],
  "18779455": [
    "featured.jpg"
  ],
  "18355804": [
    "featured.jpg"
  ],
  "18928993": [
    "featured.jpg",
    "menu3.jpg",
    "menu2.jpg",
    "menu1.jpg"
  ],
  "18745466": [
    "featured.jpg",
    "menu9.jpg",
    "menu8.jpg",
    "menu3.jpg",
    "menu2.jpg",
    "menu1.jpg",
    "menu5.jpg",
    "menu4.jpg",
    "menu6.jpg",
    "menu7.jpg",
    "menu10.jpg",
    "menu11.jpg",
    "menu13.jpg",
    "menu12.jpg",
    "menu15.jpg",
    "menu14.jpg"
  ],
  "18806342": [
    "featured.jpg"
  ],
  "18554218": [
    "featured.jpg",
    "menu3.jpg",
    "menu2.jpg",
    "menu1.jpg",
    "menu5.jpg",
    "menu4.jpg"
  ],
  "16610504": [
    "featured.jpg"
  ],
  "19043084": [
    "featured.jpg",
    "menu3.jpg",
    "menu2.jpg",
    "menu1.jpg",
    "menu4.jpg"
  ],
  "18373106": [
    "featured.jpg"
  ],
  "18545355": [
    "featured.jpg",
    "menu.jpg"
  ],
  "16601818": [
    "featured.jpg"
  ],
  "17841704": [
    "featured.jpg"
  ],
  "18708202": [
    "featured.jpg",
    "menu.jpg"
  ],
  "16601629": [
    "featured.jpg"
  ],
  "18316153": [
    "featured.jpg",
    "menu.jpg"
  ],
  "16601040": [
    "featured.jpg",
    "menu.jpg"
  ],
  "19129923": [
    "menu2.jpg",
    "menu1.jpg"
  ],
  "18445616": [
    "featured.jpg",
    "menu2.jpg",
    "menu1.jpg"
  ],
  "18276108": [
    "featured.jpg"
  ],
  "18538565": [
    "featured.jpg",
    "menu2.jpg",
    "menu1.jpg"
  ],
  "19021451": [
    "featured.jpg",
    "menu3.jpg",
    "menu2.jpg",
    "menu1.jpg",
    "menu4.jpg"
  ],
  "18445620": [
    "featured.jpg",
    "menu2.jpg",
    "menu1.jpg"
  ],
  "18313410": [
    "menu.jpg"
  ],
  "18810618": [
    "featured.jpg"
  ],
  "18216646": [
    "featured.jpg",
    "menu.jpg"
  ],
  "18231256": [
    "featured.jpg"
  ],
  "17989495": [
    "featured.jpg",
    "menu3.jpg",
    "menu2.jpg",
    "menu1.jpg"
  ],
  "17742597": [
    "featured.jpg",
    "menu.jpg"
  ],
  "16600739": [
    "featured.jpg"
  ],
  "18227905": [
    "featured.jpg",
    "menu3.jpg",
    "menu2.jpg",
    "menu1.jpg"
  ],
  "18925673": [
    "featured.jpg",
    "menu3.jpg",
    "menu2.jpg",
    "menu1.jpg",
    "menu4.jpg"
  ],
  "18300669": [
    "menu2.jpg",
    "menu1.jpg"
  ],
  "18445618": [
    "featured.jpg",
    "menu3.jpg",
    "menu2.jpg",
    "menu1.jpg",
    "menu4.jpg"
  ],
  "18511218": [
    "featured.jpg",
    "menu.jpg"
  ],
  "17989230": [
    "featured.jpg",
    "menu.jpg"
  ],
  "16589759": [
    "menu3.jpg",
    "menu2.jpg",
    "menu1.jpg"
  ],
  "16601674": [
    "featured.jpg",
    "menu2.jpg",
    "menu1.jpg"
  ],
  "18019700": [
    "featured.jpg",
    "menu.jpg"
  ],
  "16609284": [
    "featured.jpg"
  ],
  "18142714": [
    "featured.jpg",
    "menu.jpg"
  ],
  "16602002": [
    "featured.jpg"
  ],
  "17747277": [
    "featured.jpg",
    "menu2.jpg",
    "menu1.jpg"
  ],
  "18778970": [
    "menu2.jpg",
    "menu1.jpg"
  ],
  "16601673": [
    "featured.jpg"
  ],
  "16570056": [
    "featured.jpg"
  ],
  "16601228": [
    "featured.jpg",
    "menu2.jpg",
    "menu1.jpg"
  ],
  "16582522": [
    "featured.jpg"
  ],
  "18666790": [
    "featured.jpg",
    "menu3.jpg",
    "menu2.jpg",
    "menu1.jpg"
  ],
  "18668251": [
    "featured.jpg"
  ],
  "17989252": [
    "menu.jpg"
  ],
  "16610965": [
    "featured.jpg",
    "menu2.jpg",
    "menu1.jpg"
  ],
  "16578804": [
    "featured.jpg",
    "menu.jpg"
  ],
  "18612439": [
    "featured.jpg",
    "menu.jpg"
  ],
  "18300424": [
    "featured.jpg",
    "menu2.jpg",
    "menu1.jpg"
  ],
  "16601036": [
    "featured.jpg"
  ],
  "18866426": [
    "featured.jpg"
  ],
  "18440120": [
    "featured.jpg",
    "menu3.jpg",
    "menu2.jpg",
    "menu1.jpg"
  ],
  "18267665": [
    "menu2.jpg",
    "menu1.jpg"
  ],
  "17841727": [
    "featured.jpg"
  ],
  "18016938": [
    "featured.jpg"
  ],
  "18731501": [
    "featured.jpg"
  ],
  "17744078": [
    "featured.jpg"
  ],
  "16601054": [
    "featured.jpg",
    "menu.jpg"
  ],
  "17746576": [
    "menu2.jpg",
    "menu1.jpg"
  ],
  "16607357": [
    "featured.jpg",
    "menu.jpg"
  ],
  "16601053": [
    "featured.jpg"
  ],
  "16588890": [
    "featured.jpg"
  ],
  "16579730": [
    "featured.jpg"
  ],
  "18806304": [
    "menu9.jpg",
    "menu8.jpg",
    "menu3.jpg",
    "menu2.jpg",
    "menu1.jpg",
    "menu5.jpg",
    "menu4.jpg",
    "menu6.jpg",
    "menu7.jpg"
  ],
  "18445602": [
    "featured.jpg",
    "menu2.jpg",
    "menu1.jpg"
  ],
  "18300673": [
    "featured.jpg",
    "menu2.jpg",
    "menu1.jpg"
  ],
  "18521235": [
    "featured.jpg"
  ],
  "16601091": [
    "featured.jpg"
  ],
  "16590866": [
    "featured.jpg",
    "menu.jpg"
  ],
  "19103407": [
    "featured.jpg"
  ],
  "18640416": [
    "featured.jpg",
    "menu.jpg"
  ],
  "18416564": [
    "featured.jpg",
    "menu.jpg"
  ],
  "18633914": [
    "featured.jpg",
    "menu3.jpg",
    "menu2.jpg",
    "menu1.jpg"
  ],
  "18932472": [
    "featured.jpg"
  ],
  "17989240": [
    "featured.jpg",
    "menu.jpg"
  ],
  "16593813": [
    "featured.jpg",
    "menu2.jpg",
    "menu1.jpg"
  ],
  "16601037": [
    "featured.jpg",
    "menu2.jpg",
    "menu1.jpg"
  ],
  "16593249": [
    "featured.jpg",
    "menu9.jpg",
    "menu8.jpg",
    "menu3.jpg",
    "menu2.jpg",
    "menu1.jpg",
    "menu5.jpg",
    "menu4.jpg",
    "menu6.jpg",
    "menu7.jpg"
  ],
  "18313092": [
    "featured.jpg",
    "menu2.jpg",
    "menu1.jpg"
  ],
  "18156167": [
    "featured.jpg",
    "menu.jpg"
  ],
  "17747209": [
    "featured.jpg"
  ],
  "18300644": [
    "featured.jpg",
    "menu2.jpg",
    "menu1.jpg"
  ],
  "16582932": [
    "featured.jpg",
    "menu3.jpg",
    "menu2.jpg",
    "menu1.jpg",
    "menu5.jpg",
    "menu4.jpg"
  ],
  "16600941": [
    "featured.jpg"
  ],
  "18273654": [
    "featured.jpg",
    "menu2.jpg",
    "menu1.jpg"
  ],
  "18806305": [
    "menu3.jpg",
    "menu2.jpg",
    "menu1.jpg",
    "menu4.jpg"
  ],
  "16600510": [
    "featured.jpg",
    "menu9.jpg",
    "menu8.jpg",
    "menu3.jpg",
    "menu2.jpg",
    "menu1.jpg",
    "menu5.jpg",
    "menu4.jpg",
    "menu6.jpg",
    "menu7.jpg"
  ],
  "17986607": [
    "featured.jpg",
    "menu.jpg"
  ],
  "16598690": [
    "featured.jpg"
  ],
  "18391665": [
    "featured.jpg"
  ],
  "17714796": [
    "featured.jpg"
  ],
  "16608745": [
    "featured.jpg"
  ],
  "18445604": [
    "featured.jpg",
    "menu.jpg"
  ],
  "18551204": [
    "featured.jpg"
  ],
  "18709476": [
    "featured.jpg"
  ],
  "15545140": [
    "featured.jpg",
    "menu2.jpg",
    "menu1.jpg"
  ],
  "16582429": [
    "featured.jpg",
    "menu2.jpg",
    "menu1.jpg"
  ],
  "18022023": [
    "featured.jpg"
  ],
  "15545147": [
    "featured.jpg",
    "menu.jpg"
  ],
  "17985752": [
    "featured.jpg"
  ],
  "18445588": [
    "featured.jpg",
    "menu.jpg"
  ],
  "18398803": [
    "menu18.jpg",
    "featured.jpg",
    "menu9.jpg",
    "menu8.jpg",
    "menu3.jpg",
    "menu2.jpg",
    "menu1.jpg",
    "menu5.jpg",
    "menu4.jpg",
    "menu6.jpg",
    "menu7.jpg",
    "menu10.jpg",
    "menu11.jpg",
    "menu13.jpg",
    "menu12.jpg",
    "menu16.jpg",
    "menu17.jpg",
    "menu15.jpg",
    "menu14.jpg"
  ],
  "16716223": [
    "featured.jpg",
    "menu.jpg"
  ],
  "18413596": [
    "featured.jpg"
  ],
  "16601915": [
    "menu.jpg"
  ],
  "16599601": [
    "featured.jpg",
    "menu.jpg"
  ],
  "16601111": [
    "featured.jpg"
  ],
  "16566038": [
    "menu.jpg"
  ],
  "16586212": [
    "featured.jpg"
  ],
  "16588986": [
    "featured.jpg",
    "menu2.jpg",
    "menu1.jpg"
  ],
  "19104302": [
    "featured.jpg"
  ],
  "18423961": [
    "featured.jpg",
    "menu3.jpg",
    "menu2.jpg",
    "menu1.jpg",
    "menu5.jpg",
    "menu4.jpg",
    "menu6.jpg"
  ],
  "16614235": [
    "featured.jpg"
  ],
  "18561635": [
    "featured.jpg"
  ],
  "16594976": [
    "featured.jpg",
    "menu.jpg"
  ],
  "18407109": [
    "featured.jpg",
    "menu.jpg"
  ],
  "19099495": [
    "featured.jpg"
  ],
  "19159355": [
    "featured.jpg"
  ],
  "15545125": [
    "featured.jpg",
    "menu.jpg"
  ],
  "18989244": [
    "menu.jpg"
  ],
  "16585204": [
    "featured.jpg",
    "menu.jpg"
  ],
  "17744133": [
    "featured.jpg",
    "menu2.jpg",
    "menu1.jpg"
  ],
  "16567144": [
    "featured.jpg",
    "menu.jpg"
  ],
  "19011552": [
    "featured.jpg",
    "menu2.jpg",
    "menu1.jpg"
  ],
  "18409264": [
    "featured.jpg",
    "menu.jpg"
  ],
  "17841698": [
    "featured.jpg"
  ],
  "15545148": [
    "featured.jpg",
    "menu.jpg"
  ],
  "18647722": [
    "featured.jpg",
    "menu.jpg"
  ],
  "18362515": [
    "menu2.jpg",
    "menu1.jpg"
  ],
  "19103378": [
    "menu.jpg"
  ],
  "16586624": [
    "featured.jpg",
    "menu.jpg"
  ],
  "16542099": [
    "featured.jpg"
  ],
  "16601922": [
    "featured.jpg"
  ],
  "16565813": [
    "featured.jpg"
  ],
  "18614420": [
    "menu.jpg"
  ],
  "19020871": [
    "menu2.jpg",
    "menu1.jpg"
  ],
  "17841639": [
    "featured.jpg",
    "menu2.jpg",
    "menu1.jpg"
  ],
  "18178325": [
    "featured.jpg",
    "menu2.jpg",
    "menu1.jpg"
  ],
  "16613884": [
    "featured.jpg"
  ],
  "17881843": [
    "menu3.jpg",
    "menu2.jpg",
    "menu1.jpg",
    "menu4.jpg"
  ],
  "16582087": [
    "featured.jpg",
    "menu.jpg"
  ],
  "16592087": [
    "featured.jpg",
    "menu.jpg"
  ],
  "16601724": [
    "featured.jpg"
  ],
  "19005950": [
    "featured.jpg",
    "menu.jpg"
  ],
  "18701488": [
    "featured.jpg",
    "menu.jpg"
  ],
  "18657521": [
    "featured.jpg",
    "menu.jpg"
  ],
  "18897464": [
    "featured.jpg"
  ],
  "19139425": [
    "menu.jpg"
  ],
  "17714817": [
    "featured.jpg"
  ],
  "18342179": [
    "featured.jpg",
    "menu3.jpg",
    "menu2.jpg",
    "menu1.jpg",
    "menu5.jpg",
    "menu4.jpg"
  ],
  "16589638": [
    "featured.jpg",
    "menu.jpg"
  ],
  "17747123": [
    "featured.jpg"
  ],
  "15546331": [
    "menu2.jpg",
    "menu1.jpg"
  ],
  "16600866": [
    "featured.jpg",
    "menu.jpg"
  ],
  "16591062": [
    "menu9.jpg",
    "menu8.jpg",
    "menu3.jpg",
    "menu2.jpg",
    "menu1.jpg",
    "menu5.jpg",
    "menu4.jpg",
    "menu6.jpg",
    "menu7.jpg",
    "menu10.jpg"
  ],
  "16566052": [
    "featured.jpg",
    "menu.jpg"
  ],
  "17744375": [
    "featured.jpg",
    "menu.jpg"
  ],
  "18139992": [
    "featured.jpg",
    "menu.jpg"
  ],
  "16601138": [
    "featured.jpg"
  ],
  "18445590": [
    "featured.jpg",
    "menu.jpg"
  ],
  "18681877": [
    "featured.jpg",
    "menu2.jpg",
    "menu1.jpg"
  ],
  "16601599": [
    "featured.jpg"
  ],
  "17746289": [
    "featured.jpg",
    "menu.jpg"
  ],
  "18398486": [
    "featured.jpg",
    "menu.jpg"
  ],
  "16600847": [
    "featured.jpg"
  ],
  "19062045": [
    "featured.jpg"
  ],
  "16582661": [
    "featured.jpg",
    "menu.jpg"
  ],
  "16601992": [
    "featured.jpg",
    "menu.jpg"
  ],
  "18533064": [
    "featured.jpg",
    "menu.jpg"
  ],
  "16589048": [
    "featured.jpg"
  ],
  "18275831": [
    "featured.jpg",
    "menu.jpg"
  ],
  "17744548": [
    "featured.jpg"
  ],
  "18839415": [
    "menu.jpg"
  ],
  "16565892": [
    "featured.jpg",
    "menu3.jpg",
    "menu2.jpg",
    "menu1.jpg"
  ],
  "17841273": [
    "featured.jpg"
  ],
  "15548214": [
    "featured.jpg",
    "menu.jpg"
  ],
  "18735866": [
    "featured.jpg"
  ],
  "18398487": [
    "featured.jpg",
    "menu3.jpg",
    "menu2.jpg",
    "menu1.jpg",
    "menu5.jpg",
    "menu4.jpg"
  ],
  "16589674": [
    "featured.jpg"
  ],
  "16594769": [
    "featured.jpg",
    "menu2.jpg",
    "menu1.jpg"
  ],
  "17989516": [
    "featured.jpg",
    "menu.jpg"
  ],
  "16565205": [
    "featured.jpg",
    "menu.jpg"
  ],
  "19004668": [
    "menu2.jpg",
    "menu1.jpg"
  ],
  "17989529": [
    "featured.jpg",
    "menu.jpg"
  ],
  "18139993": [
    "featured.jpg"
  ],
  "16580367": [
    "featured.jpg"
  ],
  "18445596": [
    "featured.jpg",
    "menu.jpg"
  ],
  "18598320": [
    "featured.jpg",
    "menu.jpg"
  ],
  "16610443": [
    "featured.jpg"
  ],
  "16588362": [
    "featured.jpg"
  ],
  "16583117": [
    "menu3.jpg",
    "menu2.jpg",
    "menu1.jpg"
  ],
  "17748174": [
    "featured.jpg"
  ],
  "16582835": [
    "featured.jpg",
    "menu.jpg"
  ],
  "18620187": [
    "featured.jpg",
    "menu2.jpg",
    "menu1.jpg"
  ],
  "16604335": [
    "featured.jpg"
  ],
  "16604332": [
    "featured.jpg"
  ],
  "18398304": [
    "featured.jpg",
    "menu8.jpg",
    "menu3.jpg",
    "menu2.jpg",
    "menu1.jpg",
    "menu5.jpg",
    "menu4.jpg",
    "menu6.jpg",
    "menu7.jpg"
  ],
  "18170078": [
    "featured.jpg"
  ],
  "17989259": [
    "featured.jpg",
    "menu.jpg"
  ],
  "16576165": [
    "featured.jpg",
    "menu.jpg"
  ],
  "16599551": [
    "featured.jpg",
    "menu2.jpg",
    "menu1.jpg"
  ],
  "16585758": [
    "featured.jpg",
    "menu.jpg"
  ],
  "16601073": [
    "menu.jpg"
  ],
  "19185089": [
    "featured.jpg"
  ],
  "17986621": [
    "featured.jpg"
  ],
  "18413632": [
    "featured.jpg"
  ],
  "18300662": [
    "featured.jpg",
    "menu3.jpg",
    "menu2.jpg",
    "menu1.jpg",
    "menu5.jpg",
    "menu4.jpg"
  ],
  "17841339": [
    "featured.jpg"
  ],
  "18755039": [
    "menu3.jpg",
    "menu2.jpg",
    "menu1.jpg"
  ],
  "16601846": [
    "featured.jpg",
    "menu.jpg"
  ],
  "16597099": [
    "featured.jpg",
    "menu2.jpg",
    "menu1.jpg"
  ],
  "18445614": [
    "featured.jpg",
    "menu.jpg"
  ],
  "17748099": [
    "featured.jpg",
    "menu.jpg"
  ],
  "18604722": [
    "featured.jpg",
    "menu.jpg"
  ],
  "16611072": [
    "featured.jpg"
  ],
  "18574089": [
    "featured.jpg",
    "menu2.jpg",
    "menu1.jpg"
  ],
  "16584614": [
    "featured.jpg",
    "menu.jpg"
  ],
  "16600769": [
    "featured.jpg"
  ],
  "19159652": [
    "menu.jpg"
  ],
  "18074907": [
    "featured.jpg",
    "menu3.jpg",
    "menu2.jpg",
    "menu1.jpg"
  ],
  "18564027": [
    "featured.jpg",
    "menu.jpg"
  ],
  "18703418": [
    "featured.jpg",
    "menu.jpg"
  ],
  "18861279": [
    "featured.jpg",
    "menu3.jpg",
    "menu2.jpg",
    "menu1.jpg",
    "menu4.jpg"
  ],
  "19041173": [
    "featured.jpg"
  ],
  "18403868": [
    "featured.jpg",
    "menu3.jpg",
    "menu2.jpg",
    "menu1.jpg"
  ],
  "18793784": [
    "menu3.jpg",
    "menu2.jpg",
    "menu1.jpg"
  ],
  "16582912": [
    "menu2.jpg",
    "menu1.jpg"
  ],
  "17745773": [
    "featured.jpg",
    "menu.jpg"
  ],
  "18542545": [
    "featured.jpg"
  ],
  "18854757": [
    "featured.jpg"
  ],
  "18445624": [
    "menu2.jpg",
    "menu1.jpg"
  ],
  "16598816": [
    "menu.jpg"
  ],
  "18285753": [
    "featured.jpg",
    "menu.jpg"
  ],
  "18227906": [
    "featured.jpg"
  ],
  "18305549": [
    "featured.jpg"
  ],
  "17742752": [
    "featured.jpg",
    "menu9.jpg",
    "menu8.jpg",
    "menu3.jpg",
    "menu2.jpg",
    "menu1.jpg",
    "menu5.jpg",
    "menu4.jpg",
    "menu6.jpg",
    "menu7.jpg",
    "menu10.jpg",
    "menu11.jpg",
    "menu13.jpg",
    "menu12.jpg"
  ],
  "18162512": [
    "featured.jpg",
    "menu2.jpg",
    "menu1.jpg"
  ],
  "16601416": [
    "featured.jpg",
    "menu3.jpg",
    "menu2.jpg",
    "menu1.jpg",
    "menu4.jpg"
  ],
  "16610756": [
    "featured.jpg"
  ],
  "16601072": [
    "featured.jpg"
  ],
  "16612657": [
    "featured.jpg"
  ],
  "18806307": [
    "menu8.jpg",
    "menu3.jpg",
    "menu2.jpg",
    "menu1.jpg",
    "menu5.jpg",
    "menu4.jpg",
    "menu6.jpg",
    "menu7.jpg"
  ],
  "16601434": [
    "featured.jpg",
    "menu.jpg"
  ],
  "16601601": [
    "featured.jpg",
    "menu.jpg"
  ],
  "16601057": [
    "featured.jpg",
    "menu.jpg"
  ],
  "18811515": [
    "featured.jpg",
    "menu2.jpg",
    "menu1.jpg"
  ],
  "19109366": [
    "featured.jpg",
    "menu.jpg"
  ],
  "18445606": [
    "menu2.jpg",
    "menu1.jpg"
  ],
  "19133034": [
    "featured.jpg",
    "menu3.jpg",
    "menu2.jpg",
    "menu1.jpg",
    "menu5.jpg",
    "menu4.jpg"
  ],
  "17841741": [
    "featured.jpg"
  ],
  "18273651": [
    "featured.jpg"
  ],
  "16601092": [
    "featured.jpg"
  ],
  "16594432": [
    "featured.jpg"
  ],
  "16600716": [
    "featured.jpg",
    "menu.jpg"
  ],
  "16601059": [
    "featured.jpg"
  ],
  "19205919": [
    "menu2.jpg",
    "menu1.jpg"
  ],
  "18463355": [
    "featured.jpg",
    "menu2.jpg",
    "menu1.jpg"
  ],
  "19182828": [
    "menu3.jpg",
    "menu2.jpg",
    "menu1.jpg"
  ],
  "18822336": [
    "featured.jpg"
  ],
  "18424005": [
    "featured.jpg",
    "menu.jpg"
  ],
  "15547361": [
    "featured.jpg",
    "menu.jpg"
  ],
  "18673432": [
    "featured.jpg",
    "menu.jpg"
  ],
  "19087287": [
    "featured.jpg",
    "menu2.jpg",
    "menu1.jpg"
  ],
  "17747097": [
    "featured.jpg",
    "menu.jpg"
  ],
  "16612242": [
    "featured.jpg",
    "menu2.jpg",
    "menu1.jpg"
  ],
  "19182826": [
    "menu3.jpg",
    "menu2.jpg",
    "menu1.jpg"
  ],
  "18348731": [
    "featured.jpg"
  ],
  "17849576": [
    "featured.jpg",
    "menu.jpg"
  ],
  "16575708": [
    "menu2.jpg",
    "menu1.jpg"
  ],
  "17989242": [
    "featured.jpg",
    "menu.jpg"
  ],
  "18707404": [
    "menu.jpg"
  ],
  "16560286": [
    "featured.jpg",
    "menu3.jpg",
    "menu2.jpg",
    "menu1.jpg",
    "menu5.jpg",
    "menu4.jpg"
  ],
  "16599545": [
    "featured.jpg"
  ],
  "16582909": [
    "menu3.jpg",
    "menu2.jpg",
    "menu1.jpg",
    "menu4.jpg"
  ],
  "16594606": [
    "featured.jpg",
    "menu3.jpg",
    "menu2.jpg",
    "menu1.jpg",
    "menu5.jpg",
    "menu4.jpg",
    "menu6.jpg"
  ],
  "18665166": [
    "featured.jpg"
  ],
  "18474981": [
    "featured.jpg"
  ],
  "19032862": [
    "featured.jpg",
    "menu9.jpg",
    "menu8.jpg",
    "menu3.jpg",
    "menu2.jpg",
    "menu1.jpg",
    "menu5.jpg",
    "menu4.jpg",
    "menu6.jpg",
    "menu7.jpg",
    "menu10.jpg",
    "menu11.jpg",
    "menu13.jpg",
    "menu12.jpg",
    "menu15.jpg",
    "menu14.jpg"
  ],
  "17742776": [
    "featured.jpg",
    "menu3.jpg",
    "menu2.jpg",
    "menu1.jpg"
  ],
  "16601056": [
    "featured.jpg"
  ],
  "16609204": [
    "featured.jpg"
  ],
  "18431123": [
    "featured.jpg",
    "menu.jpg"
  ],
  "18445600": [
    "featured.jpg",
    "menu.jpg"
  ],
  "18600799": [
    "featured.jpg",
    "menu.jpg"
  ],
  "16588455": [
    "featured.jpg",
    "menu3.jpg",
    "menu2.jpg",
    "menu1.jpg",
    "menu4.jpg"
  ],
  "18393539": [
    "featured.jpg"
  ],
  "19182820": [
    "featured.jpg",
    "menu2.jpg",
    "menu1.jpg"
  ],
  "18372834": [
    "featured.jpg",
    "menu.jpg"
  ],
  "19095585": [
    "menu.jpg"
  ],
  "18853391": [
    "featured.jpg",
    "menu2.jpg",
    "menu1.jpg"
  ],
  "16592593": [
    "featured.jpg",
    "menu.jpg"
  ],
  "18822330": [
    "featured.jpg",
    "menu.jpg"
  ],
  "18198076": [
    "featured.jpg"
  ],
  "16604310": [
    "featured.jpg"
  ],
  "18340761": [
    "menu.jpg"
  ],
  "16601033": [
    "menu.jpg"
  ],
  "18286356": [
    "featured.jpg",
    "menu3.jpg",
    "menu2.jpg",
    "menu1.jpg"
  ],
  "16603888": [
    "featured.jpg"
  ],
  "16600067": [
    "featured.jpg"
  ],
  "18051127": [
    "featured.jpg",
    "menu.jpg"
  ],
  "18839632": [
    "featured.jpg",
    "menu.jpg"
  ],
  "16599651": [
    "featured.jpg",
    "menu2.jpg",
    "menu1.jpg"
  ],
  "16595262": [
    "featured.jpg",
    "menu.jpg"
  ],
  "18886728": [
    "featured.jpg"
  ],
  "18751763": [
    "featured.jpg",
    "menu3.jpg",
    "menu2.jpg",
    "menu1.jpg"
  ],
  "18046507": [
    "featured.jpg",
    "menu.jpg"
  ],
  "15545117": [
    "featured.jpg",
    "menu.jpg"
  ],
  "16584583": [
    "featured.jpg",
    "menu2.jpg",
    "menu1.jpg"
  ],
  "16599832": [
    "featured.jpg",
    "menu.jpg"
  ],
  "16601513": [
    "featured.jpg",
    "menu.jpg"
  ],
  "17743771": [
    "featured.jpg",
    "menu.jpg"
  ],
  "19139427": [
    "featured.jpg",
    "menu2.jpg",
    "menu1.jpg"
  ],
  "18695466": [
    "featured.jpg",
    "menu3.jpg",
    "menu2.jpg",
    "menu1.jpg",
    "menu4.jpg"
  ],
  "16581638": [
    "featured.jpg",
    "menu.jpg"
  ],
  "17841603": [
    "featured.jpg",
    "menu.jpg"
  ],
  "16597557": [
    "featured.jpg",
    "menu2.jpg",
    "menu1.jpg"
  ],
  "19103389": [
    "featured.jpg",
    "menu2.jpg",
    "menu1.jpg"
  ],
  "18781125": [
    "featured.jpg",
    "menu3.jpg",
    "menu2.jpg",
    "menu1.jpg"
  ],
  "16602307": [
    "featured.jpg",
    "menu.jpg"
  ],
  "18022016": [
    "featured.jpg",
    "menu.jpg"
  ],
  "18199288": [
    "featured.jpg",
    "menu.jpg"
  ],
  "18654901": [
    "featured.jpg",
    "menu3.jpg",
    "menu2.jpg",
    "menu1.jpg"
  ],
  "18391341": [
    "featured.jpg",
    "menu3.jpg",
    "menu2.jpg",
    "menu1.jpg"
  ],
  "18360429": [
    "featured.jpg",
    "menu.jpg"
  ],
  "16578959": [
    "featured.jpg",
    "menu2.jpg",
    "menu1.jpg"
  ],
  "19139426": [
    "featured.jpg",
    "menu.jpg"
  ],
  "18463211": [
    "featured.jpg",
    "menu.jpg"
  ],
  "18560512": [
    "featured.jpg"
  ],
  "16588526": [
    "featured.jpg",
    "menu.jpg"
  ],
  "17744304": [
    "featured.jpg",
    "menu.jpg"
  ],
  "18317985": [
    "menu.jpg"
  ],
  "17743325": [
    "featured.jpg",
    "menu.jpg"
  ],
  "19126296": [
    "featured.jpg"
  ],
  "19103328": [
    "featured.jpg"
  ],
  "17965913": [
    "featured.jpg",
    "menu.jpg"
  ],
  "16600831": [
    "featured.jpg"
  ],
  "18781123": [
    "featured.jpg",
    "menu.jpg"
  ],
  "17747379": [
    "featured.jpg",
    "menu.jpg"
  ],
  "15547240": [
    "featured.jpg"
  ],
  "16584389": [
    "featured.jpg",
    "menu2.jpg",
    "menu1.jpg"
  ],
  "19094328": [
    "featured.jpg"
  ],
  "17746294": [
    "featured.jpg",
    "menu.jpg"
  ],
  "16609983": [
    "menu.jpg"
  ],
  "16599603": [
    "featured.jpg"
  ],
  "18245073": [
    "featured.jpg",
    "menu2.jpg",
    "menu1.jpg"
  ],
  "18445584": [
    "featured.jpg",
    "menu.jpg"
  ],
  "18812476": [
    "menu.jpg"
  ],
  "18607468": [
    "featured.jpg"
  ],
  "18621161": [
    "featured.jpg",
    "menu2.jpg",
    "menu1.jpg"
  ],
  "18527611": [
    "featured.jpg",
    "menu.jpg"
  ],
  "16568959": [
    "featured.jpg",
    "menu.jpg"
  ],
  "16583363": [
    "featured.jpg",
    "menu.jpg"
  ],
  "18022026": [
    "featured.jpg",
    "menu3.jpg",
    "menu2.jpg",
    "menu1.jpg"
  ]
}